block_weave/__init__.py
block_weave/core/__init__.py
block_weave/core/agent.py
block_weave/core/block.py
block_weave/core/block_type.py
block_weave/core/data_loader.py
block_weave/core/llm.py
block_weave/core/prompt_templates/basic1.md
block_weave/core/prompt_templates/function.md
block_weave-0.0.1.dist-info/METADATA
block_weave-0.0.1.dist-info/WHEEL
block_weave-0.0.1.dist-info/licenses/LICENSE
block_weave-0.0.1.dist-info/RECORD
