Metadata-Version: 2.3
Name: block_weave
Version: 0.0.1
Summary: Build prompts like lego blocks and weave them through code like regular functions
Project-URL: Homepage, https://github.com/ThijmenVanBuuren/block_weave
Project-URL: Issues, https://github.com/ThijmenVanBuuren/block_weave/issues
Author-email: Thijmen van Buuren <thijmendeveloper@gmail.com>
License-File: LICENSE
Classifier: License :: OSI Approved :: Apache Software License
Classifier: Programming Language :: Python :: 3
Requires-Python: >=3.10
Requires-Dist: langchain-openai
Requires-Dist: ollama
Requires-Dist: python-dotenv
